Metadata-Version: 2.1
Name: codavi
Version: 0.7
Summary: Obtención de datos sobre el COVID-19
Home-page: https://github.com/manucabral/Codavi
Author: Manuel Cabral
Author-email: cabral.manuel@yandex.com
License: apache-2.0
Keywords: python,covid,covid-19,covid-argentina,covid-data
Platform: UNKNOWN
Classifier: Development Status :: 3 - Alpha
Classifier: Intended Audience :: Developers
Classifier: Topic :: Software Development :: Build Tools
Classifier: License :: OSI Approved :: Apache Software License
Classifier: Programming Language :: Python :: 3
Classifier: Programming Language :: Python :: 3.9
Classifier: Operating System :: Unix
Classifier: Operating System :: MacOS :: MacOS X
Classifier: Operating System :: Microsoft :: Windows
Requires-Python: >= 3.9
